smartdata/__init__.py
smartdata/config.py
smartdata/custom_agent.py
smartdata/memory.py
smartdata/modeler.py
smartdata/util.py
smartdataai_test-4.2.dist-info/METADATA
smartdataai_test-4.2.dist-info/WHEEL
smartdataai_test-4.2.dist-info/top_level.txt
smartdataai_test-4.2.dist-info/RECORD
